<?xml version="1.0" encoding="utf-8"?><data><SectionUsingMCOrMcr>false</SectionUsingMCOrMcr><CxilVariableGroup POUTrackingId="fdfa40cd-3852-4dc6-9263-1976e23bf86a" /><CxilVariable CxilVariableType="FunctionResult" DataType="STRING[1986]" Name="_tmpRslt_STRING1986" InitialValue="" IsAddedInOnlineEdit="false" Order="" /><CxilVariable CxilVariableType="PowerFlow" DataType="BOOL" Name="_tmpPF0" InitialValue="" IsAddedInOnlineEdit="false" Order="" /><CxilLinkInformationListTable><CxilLinkInformationList Offset="10" FileNameWithoutExtension="SubProgram_ee087915ea0e4b3c8ad7adbd873b5d9e_0"><ElementUriList ElementUriList="" /><ElementUriList ElementUriList="/Rung%5B0%5D/Element%5B376318e3-875e-4c42-80ed-6e3d00000002%5D" /><ElementUriList ElementUriList="" /><ElementUriList ElementUriList="/Rung%5B0%5D/Element%5B376318e3-875e-4c42-80ed-6e3d00000008%5D" /><ElementUriList ElementUriList="" /><ElementUriList ElementUriList="" /><ElementUriList ElementUriList="/Rung%5B1%5D/Element%5B376318e3-875e-4c42-80ed-6e3d0000000c%5D" /><ElementUriList ElementUriList="" /><ElementUriList ElementUriList="" /><ElementUriList ElementUriList="/Rung%5B1%5D/Element%5B376318e3-875e-4c42-80ed-6e3d0000000c%5D/Line%5B1%5D" /><ElementUriList ElementUriList="" /><ElementUriList ElementUriList="" /><ElementUriList ElementUriList="" /></CxilLinkInformationList></CxilLinkInformationListTable><CxilDivisionInformation><CxilDivision FileNameWithoutExtension="SubProgram_ee087915ea0e4b3c8ad7adbd873b5d9e_0" ProgramBlockName="m_analog_0" FirstNumber="0" Count="2" /></CxilDivisionInformation></data>